Workbook

Sheet Dashboard
A1: GCP Pricing Cost Analysis
A2: Source: Pricing for Billing Account 1.numbers. The source contains pricing rows only; enter usage on the Usage Inputs sheet to estimate actual expense.
A4: Pricing rows | E4: Unique services
A5: 109 | E5: 12
A7: Unique SKUs | E7: Chargeable rows
A8: 46 | E8: 80
A10: Free/zero rows | E10: CUD rows
A11: 29 | E11: 32
A14: Key findings
A15: This is a pricing catalog, not an invoice or billing export. Actual expense requires monthly usage quantities.
A16: Network egress is the main usage-sensitive risk: Cloud Run, Cloud Storage, Artifact Registry, and Cloud Build include egress SKUs up to INR 17.9645 per GiB.
A17: Cloud Logging becomes material after the 50 GiB free tier at INR 47.275 per GiB.
A18: Cloud Run has many CUD rows; request charges show about 17.0% lower rates under listed CUD models versus default.
A19: Fixed domain registration is INR 1,134.60 yearly per .com, approximately INR 94.55 per month.
A20: Use the Expense Estimator sheet for tier-aware estimates from entered usage volumes.
A23: Top raw list-price rows
A24: Service | B24: SKU description | C24: Unit | D24: Tier start | E24: List price (INR)
A25: Cloud Pub/Sub | B25: Message Delivery Basic | C25: tebibyte | D25: 0.009765625 | E25: 3782
A26: Cloud Domains | B26: Subscription for domain with TLD .com - yearly prepay | C26: year | D26: 0 | E26: 1134.6
A27: Cloud Logging | B27: Log Storage cost | C27: gibibyte | D27: 50 | E27: 47.275
A28: Cloud DNS | B28: DNS Query (port 53) | C28: count | D28: 0 | E28: 37.82
A29: Cloud Tasks | B29: Operations | C29: count | D29: 1000000 | E29: 37.82
A30: Cloud Run | B30: Requests | C30: count | D30: 2000000 | E30: 37.82
A31: Cloud Run | B31: Requests | C31: count | D31: 2000000 | E31: 31.3906
A32: Cloud Run | B32: Requests | C32: count | D32: 2000000 | E32: 31.3906

Sheet Pricing Summary
A1: Pricing Summary
A2: Service and cost-category summary derived from the source pricing catalog.
A4: Service | B4: Unique SKUs | C4: Pricing rows | D4: Chargeable rows | E4: Free/zero rows | F4: Default rows | G4: CUD rows | H4: Max raw list price (INR) | I4: Cost categories | J4: Units
A5: Cloud Run | B5: 15 | C5: 57 | D5: 47 | E5: 10 | F5: 25 | G5: 32 | H5: 37.82 | I5: Compute time, Network / egress, Requests / operations | J5: count, gibibyte, gibibyte second, second
A6: Cloud Storage | B6: 10 | C6: 16 | D6: 12 | E6: 4 | F6: 16 | G6: 0 | H6: 11.346 | I6: Network / egress, Storage / retention | J6: count, gibibyte, gibibyte month
A7: Artifact Registry | B7: 5 | C7: 8 | D7: 5 | E7: 3 | F7: 8 | G7: 0 | H7: 11.346 | I7: Network / egress, Storage / retention | J7: gibibyte, gibibyte month
A8: Cloud DNS | B8: 2 | C8: 5 | D8: 5 | E8: 0 | F8: 5 | G8: 0 | H8: 37.82 | I8: Other, Requests / operations | J8: count, month
A9: Cloud Build | B9: 2 | C9: 5 | D9: 4 | E9: 1 | F9: 5 | G9: 0 | H9: 11.346 | I9: Compute time, Network / egress | J9: gibibyte, minute
A10: Secret Manager | B10: 2 | C10: 4 | D10: 2 | E10: 2 | F10: 4 | G10: 0 | H10: 5.673 | I10: Requests / operations, Storage / retention | J10: count, month
A11: Cloud Domains | B11: 1 | C11: 1 | D11: 1 | E11: 0 | F11: 1 | G11: 0 | H11: 1134.6 | I11: Fixed subscription | J11: year
A12: Cloud Logging | B12: 1 | C12: 2 | D12: 1 | E12: 1 | F12: 2 | G12: 0 | H12: 47.275 | I12: Storage / retention | J12: gibibyte
A13: Cloud Pub/Sub | B13: 1 | C13: 2 | D13: 1 | E13: 1 | F13: 2 | G13: 0 | H13: 3782 | I13: Requests / operations | J13: tebibyte
A14: Cloud Scheduler | B14: 1 | C14: 2 | D14: 1 | E14: 1 | F14: 2 | G14: 0 | H14: 9.455 | I14: Other | J14: count
A15: Cloud Tasks | B15: 2 | C15: 3 | D15: 1 | E15: 2 | F15: 3 | G15: 0 | H15: 37.82 | I15: Network / egress, Requests / operations | J15: count, gibibyte
A16: Cloud SQL | B16: 4 | C16: 4 | D16: 0 | E16: 4 | F16: 4 | G16: 0 | H16: 0 | I16: Compute time, Other, Storage / retention | J16: gibibyte hour, gibibyte month, hour
A20: Category | B20: Rows | C20: Chargeable rows | D20: Free/zero rows | E20: Max normalized rate | F20: Normalized unit
A21: Compute time | B21: 33 | C21: 31 | D21: 2 | E21: 8.16912 | F21: per hour
A22: Fixed subscription | B22: 1 | C22: 1 | D22: 0 | E22: 94.55 | F22: per month equivalent
A23: Network / egress | B23: 34 | C23: 25 | D23: 9 | E23: 17.9645 | F23: per gibibyte
A24: Other | B24: 6 | C24: 4 | D24: 2 | E24: 18.91 | F24: per month
A25: Requests / operations | B25: 18 | C25: 10 | D25: 8 | E25: 37.82 | F25: per 1,000,000 count
A26: Storage / retention | B26: 17 | C26: 9 | D26: 8 | E26: 47.275 | F26: per gibibyte

Sheet Usage Inputs
A1: Usage Inputs
A2: Enter expected monthly usage by SKU. Blue/yellow cells drive the Expense Estimator formulas.
A4: Service | B4: SKU ID | C4: SKU description | D4: Category | E4: Usage unit | F4: Per unit quantity | G4: Monthly usage input | H4: Input notes | I4: Pricing model
A5: Artifact Registry | B5: E794-0787-45A9 | C5: Artifact Registry GOOGLE-API Egress | D5: Network / egress | E5: gibibyte | F5: 1 | G5: 0 | I5: Default
A6: Artifact Registry | B6: 173D-B415-5815 | C6: Artifact Registry Network Inter Region Egress North America to North America | D6: Network / egress | E6: gibibyte | F6: 1 | G6: 0 | I6: Default
A7: Artifact Registry | B7: 72BD-5309-1C4C | C7: Artifact Registry Network Internet Egress Intercontinental (Excl Oceania, Africa and China) | D7: Network / egress | E7: gibibyte | F7: 1 | G7: 0 | I7: Default
A8: Artifact Registry | B8: 546B-E8F2-6FF5 | C8: Artifact Registry Network Intra Region Egress | D8: Network / egress | E8: gibibyte | F8: 1 | G8: 0 | I8: Default
A9: Artifact Registry | B9: 8502-299A-ABAF | C9: Artifact Registry Storage | D9: Storage / retention | E9: gibibyte month | F9: 1 | G9: 0 | I9: Default
A10: Cloud Build | B10: A464-9020-6404 | C10: Build time e2-standard-2 | D10: Compute time | E10: minute | F10: 1 | G10: 0 | I10: Default
A11: Cloud Build | B11: D5F9-06F3-71E0 | C11: Cloud Build: Network Data Transfer Out Internet Premium within North America | D11: Network / egress | E11: gibibyte | F11: 1 | G11: 0 | I11: Default
A12: Cloud DNS | B12: 6DFF-5025-A128 | C12: DNS Query (port 53) | D12: Requests / operations | E12: count | F12: 1000000 | G12: 0 | I12: Default
A13: Cloud DNS | B13: 8C22-6FC3-D478 | C13: ManagedZone | D13: Other | E13: month | F13: 1 | G13: 0 | I13: Default
A14: Cloud Domains | B14: 6A79-1457-3004 | C14: Subscription for domain with TLD .com - yearly prepay | D14: Fixed subscription | E14: year | F14: 1 | G14: 0 | I14: Default
A15: Cloud Logging | B15: 143F-A1B0-E0BE | C15: Log Storage cost | D15: Storage / retention | E15: gibibyte | F15: 1 | G15: 0 | I15: Default
A16: Cloud Pub/Sub | B16: 027D-B6C7-CCA2 | C16: Message Delivery Basic | D16: Requests / operations | E16: tebibyte | F16: 1 | G16: 0 | I16: Default
... A50: Secret Manager | B50: 7756-ADEF-84F4 | C50: Secret version replica storage | D50: Storage / retention | E50: month | F50: 1 | G50: 0 | I50: Default

Sheet Expense Estimator
A1: Expense Estimator
A2: Tier-aware monthly cost estimate for Default pricing rows. Costs remain zero until usage is entered on Usage Inputs.
A4: Service | B4: SKU ID | C4: SKU description | D4: Category | E4: Unit | F4: Per unit quantity | G4: Tier start | H4: Next tier start | I4: List price (INR) | J4: Usage | K4: Billable quantity in tier | L4: Estimated monthly cost | M4: Notes | O4: Estimated monthly total
A5: Artifact Registry | B5: E794-0787-45A9 | C5: Artifact Registry GOOGLE-API Egress | D5: Network / egress | E5: gibibyte | F5: 1 | G5: 0 | I5: 0 | J5: =IFERROR(INDEX('Usage Inputs'!$G:$G,MATCH(B5,'Usage Inputs'!$B:$B,0)),0) | K5: =MAX(0,(IF(H5="",J5,MIN(J5,H5))-G5)) | L5: =K5/F5*I5 | M5: Final tier | O5: =SUM(L5:L81)
A6: Artifact Registry | B6: 173D-B415-5815 | C6: Artifact Registry Network Inter Region Egress North America to North America | D6: Network / egress | E6: gibibyte | F6: 1 | G6: 0 | I6: 0.9455 | J6: =IFERROR(INDEX('Usage Inputs'!$G:$G,MATCH(B6,'Usage Inputs'!$B:$B,0)),0) | K6: =MAX(0,(IF(H6="",J6,MIN(J6,H6))-G6)) | L6: =K6/F6*I6 | M6: Final tier
A7: Artifact Registry | B7: 72BD-5309-1C4C | C7: Artifact Registry Network Internet Egress Intercontinental (Excl Oceania, Africa and China) | D7: Network / egress | E7: gibibyte | F7: 1 | G7: 0 | H7: 10240 | I7: 11.346 | J7: =IFERROR(INDEX('Usage Inputs'!$G:$G,MATCH(B7,'Usage Inputs'!$B:$B,0)),0) | K7: =MAX(0,(IF(H7="",J7,MIN(J7,H7))-G7)) | L7: =K7/F7*I7 | M7: Bounded tier | O7: Current status
A8: Artifact Registry | B8: 72BD-5309-1C4C | C8: Artifact Registry Network Internet Egress Intercontinental (Excl Oceania, Africa and China) | D8: Network / egress | E8: gibibyte | F8: 1 | G8: 10240 | H8: 153600 | I8: 8.03675 | J8: =IFERROR(INDEX('Usage Inputs'!$G:$G,MATCH(B8,'Usage Inputs'!$B:$B,0)),0) | K8: =MAX(0,(IF(H8="",J8,MIN(J8,H8))-G8)) | L8: =K8/F8*I8 | M8: Bounded tier | O8: =IF(O5=0,"No usage entered","Usage estimate active")
A9: Artifact Registry | B9: 72BD-5309-1C4C | C9: Artifact Registry Network Internet Egress Intercontinental (Excl Oceania, Africa and China) | D9: Network / egress | E9: gibibyte | F9: 1 | G9: 153600 | I9: 7.564 | J9: =IFERROR(INDEX('Usage Inputs'!$G:$G,MATCH(B9,'Usage Inputs'!$B:$B,0)),0) | K9: =MAX(0,(IF(H9="",J9,MIN(J9,H9))-G9)) | L9: =K9/F9*I9 | M9: Final tier
A10: Artifact Registry | B10: 546B-E8F2-6FF5 | C10: Artifact Registry Network Intra Region Egress | D10: Network / egress | E10: gibibyte | F10: 1 | G10: 0 | I10: 0 | J10: =IFERROR(INDEX('Usage Inputs'!$G:$G,MATCH(B10,'Usage Inputs'!$B:$B,0)),0) | K10: =MAX(0,(IF(H10="",J10,MIN(J10,H10))-G10)) | L10: =K10/F10*I10 | M10: Final tier
A11: Artifact Registry | B11: 8502-299A-ABAF | C11: Artifact Registry Storage | D11: Storage / retention | E11: gibibyte month | F11: 1 | G11: 0 | H11: 0.5 | I11: 0 | J11: =IFERROR(INDEX('Usage Inputs'!$G:$G,MATCH(B11,'Usage Inputs'!$B:$B,0)),0) | K11: =MAX(0,(IF(H11="",J11,MIN(J11,H11))-G11)) | L11: =K11/F11*I11 | M11: Bounded tier
A12: Artifact Registry | B12: 8502-299A-ABAF | C12: Artifact Registry Storage | D12: Storage / retention | E12: gibibyte month | F12: 1 | G12: 0.5 | I12: 9.455 | J12: =IFERROR(INDEX('Usage Inputs'!$G:$G,MATCH(B12,'Usage Inputs'!$B:$B,0)),0) | K12: =MAX(0,(IF(H12="",J12,MIN(J12,H12))-G12)) | L12: =K12/F12*I12 | M12: Final tier
A13: Cloud Build | B13: A464-9020-6404 | C13: Build time e2-standard-2 | D13: Compute time | E13: minute | F13: 1 | G13: 0 | H13: 2500 | I13: 0 | J13: =IFERROR(INDEX('Usage Inputs'!$G:$G,MATCH(B13,'Usage Inputs'!$B:$B,0)),0) | K13: =MAX(0,(IF(H13="",J13,MIN(J13,H13))-G13)) | L13: =K13/F13*I13 | M13: Bounded tier
A14: Cloud Build | B14: A464-9020-6404 | C14: Build time e2-standard-2 | D14: Compute time | E14: minute | F14: 1 | G14: 2500 | I14: 0.5673 | J14: =IFERROR(INDEX('Usage Inputs'!$G:$G,MATCH(B14,'Usage Inputs'!$B:$B,0)),0) | K14: =MAX(0,(IF(H14="",J14,MIN(J14,H14))-G14)) | L14: =K14/F14*I14 | M14: Final tier
A15: Cloud Build | B15: D5F9-06F3-71E0 | C15: Cloud Build: Network Data Transfer Out Internet Premium within North America | D15: Network / egress | E15: gibibyte | F15: 1 | G15: 0 | H15: 1024 | I15: 11.346 | J15: =IFERROR(INDEX('Usage Inputs'!$G:$G,MATCH(B15,'Usage Inputs'!$B:$B,0)),0) | K15: =MAX(0,(IF(H15="",J15,MIN(J15,H15))-G15)) | L15: =K15/F15*I15 | M15: Bounded tier
A16: Cloud Build | B16: D5F9-06F3-71E0 | C16: Cloud Build: Network Data Transfer Out Internet Premium within North America | D16: Network / egress | E16: gibibyte | F16: 1 | G16: 1024 | H16: 10240 | I16: 10.4005 | J16: =IFERROR(INDEX('Usage Inputs'!$G:$G,MATCH(B16,'Usage Inputs'!$B:$B,0)),0) | K16: =MAX(0,(IF(H16="",J16,MIN(J16,H16))-G16)) | L16: =K16/F16*I16 | M16: Bounded tier
A17: Cloud Build | B17: D5F9-06F3-71E0 | C17: Cloud Build: Network Data Transfer Out Internet Premium within North America | D17: Network / egress | E17: gibibyte | F17: 1 | G17: 10240 | I17: 7.564 | J17: =IFERROR(INDEX('Usage Inputs'!$G:$G,MATCH(B17,'Usage Inputs'!$B:$B,0)),0) | K17: =MAX(0,(IF(H17="",J17,MIN(J17,H17))-G17)) | L17: =K17/F17*I17 | M17: Final tier
A18: Cloud DNS | B18: 6DFF-5025-A128 | C18: DNS Query (port 53) | D18: Requests / operations | E18: count | F18: 1000000 | G18: 0 | H18: 1000000000 | I18: 37.82 | J18: =IFERROR(INDEX('Usage Inputs'!$G:$G,MATCH(B18,'Usage Inputs'!$B:$B,0)),0) | K18: =MAX(0,(IF(H18="",J18,MIN(J18,H18))-G18)) | L18: =K18/F18*I18 | M18: Bounded tier
A19: Cloud DNS | B19: 6DFF-5025-A128 | C19: DNS Query (port 53) | D19: Requests / operations | E19: count | F19: 1000000 | G19: 1000000000 | I19: 18.91 | J19: =IFERROR(INDEX('Usage Inputs'!$G:$G,MATCH(B19,'Usage Inputs'!$B:$B,0)),0) | K19: =MAX(0,(IF(H19="",J19,MIN(J19,H19))-G19)) | L19: =K19/F19*I19 | M19: Final tier
A20: Cloud DNS | B20: 8C22-6FC3-D478 | C20: ManagedZone | D20: Other | E20: month | F20: 1 | G20: 0 | H20: 25 | I20: 18.91 | J20: =IFERROR(INDEX('Usage Inputs'!$G:$G,MATCH(B20,'Usage Inputs'!$B:$B,0)),0) | K20: =MAX(0,(IF(H20="",J20,MIN(J20,H20))-G20)) | L20: =K20/F20*I20 | M20: Bounded tier
A21: Cloud DNS | B21: 8C22-6FC3-D478 | C21: ManagedZone | D21: Other | E21: month | F21: 1 | G21: 25 | H21: 10000 | I21: 9.455 | J21: =IFERROR(INDEX('Usage Inputs'!$G:$G,MATCH(B21,'Usage Inputs'!$B:$B,0)),0) | K21: =MAX(0,(IF(H21="",J21,MIN(J21,H21))-G21)) | L21: =K21/F21*I21 | M21: Bounded tier
A22: Cloud DNS | B22: 8C22-6FC3-D478 | C22: ManagedZone | D22: Other | E22: month | F22: 1 | G22: 10000 | I22: 2.8365 | J22: =IFERROR(INDEX('Usage Inputs'!$G:$G,MATCH(B22,'Usage Inputs'!$B:$B,0)),0) | K22: =MAX(0,(IF(H22="",J22,MIN(J22,H22))-G22)) | L22: =K22/F22*I22 | M22: Final tier
A23: Cloud Domains | B23: 6A79-1457-3004 | C23: Subscription for domain with TLD .com - yearly prepay | D23: Fixed subscription | E23: year | F23: 1 | G23: 0 | I23: 1134.6 | J23: =IFERROR(INDEX('Usage Inputs'!$G:$G,MATCH(B23,'Usage Inputs'!$B:$B,0)),0) | K23: =MAX(0,(IF(H23="",J23,MIN(J23,H23))-G23)) | L23: =K23/F23*I23 | M23: Final tier
A24: Cloud Logging | B24: 143F-A1B0-E0BE | C24: Log Storage cost | D24: Storage / retention | E24: gibibyte | F24: 1 | G24: 0 | H24: 50 | I24: 0 | J24: =IFERROR(INDEX('Usage Inputs'!$G:$G,MATCH(B24,'Usage Inputs'!$B:$B,0)),0) | K24: =MAX(0,(IF(H24="",J24,MIN(J24,H24))-G24)) | L24: =K24/F24*I24 | M24: Bounded tier
A25: Cloud Logging | B25: 143F-A1B0-E0BE | C25: Log Storage cost | D25: Storage / retention | E25: gibibyte | F25: 1 | G25: 50 | I25: 47.275 | J25: =IFERROR(INDEX('Usage Inputs'!$G:$G,MATCH(B25,'Usage Inputs'!$B:$B,0)),0) | K25: =MAX(0,(IF(H25="",J25,MIN(J25,H25))-G25)) | L25: =K25/F25*I25 | M25: Final tier
A26: Cloud Pub/Sub | B26: 027D-B6C7-CCA2 | C26: Message Delivery Basic | D26: Requests / operations | E26: tebibyte | F26: 1 | G26: 0 | H26: 0.009765625 | I26: 0 | J26: =IFERROR(INDEX('Usage Inputs'!$G:$G,MATCH(B26,'Usage Inputs'!$B:$B,0)),0) | K26: =MAX(0,(IF(H26="",J26,MIN(J26,H26))-G26)) | L26: =K26/F26*I26 | M26: Bounded tier
A27: Cloud Pub/Sub | B27: 027D-B6C7-CCA2 | C27: Message Delivery Basic | D27: Requests / operations | E27: tebibyte | F27: 1 | G27: 0.009765625 | I27: 3782 | J27: =IFERROR(INDEX('Usage Inputs'!$G:$G,MATCH(B27,'Usage Inputs'!$B:$B,0)),0) | K27: =MAX(0,(IF(H27="",J27,MIN(J27,H27))-G27)) | L27: =K27/F27*I27 | M27: Final tier
A28: Cloud Run | B28: 0CCB-7057-48DE | C28: Cloud Run GOOGLE-API Data Transfer Out | D28: Network / egress | E28: gibibyte | F28: 1 | G28: 0 | I28: 0 | J28: =IFERROR(INDEX('Usage Inputs'!$G:$G,MATCH(B28,'Usage Inputs'!$B:$B,0)),0) | K28: =MAX(0,(IF(H28="",J28,MIN(J28,H28))-G28)) | L28: =K28/F28*I28 | M28: Final tier
A29: Cloud Run | B29: D63C-EDCA-4726 | C29: Cloud Run Network Data Transfer Out via Carrier Peering Network - North America Based | D29: Network / egress | E29: gibibyte | F29: 1 | G29: 0 | I29: 1.891 | J29: =IFERROR(INDEX('Usage Inputs'!$G:$G,MATCH(B29,'Usage Inputs'!$B:$B,0)),0) | K29: =MAX(0,(IF(H29="",J29,MIN(J29,H29))-G29)) | L29: =K29/F29*I29 | M29: Final tier
A30: Cloud Run | B30: 9B46-8DDB-2AC8 | C30: Cloud Run Network Inter Region Data Transfer Out Intercontinental (Excl Oceania) | D30: Network / egress | E30: gibibyte | F30: 1 | G30: 0 | H30: 1 | I30: 0 | J30: =IFERROR(INDEX('Usage Inputs'!$G:$G,MATCH(B30,'Usage Inputs'!$B:$B,0)),0) | K30: =MAX(0,(IF(H30="",J30,MIN(J30,H30))-G30)) | L30: =K30/F30*I30 | M30: Bounded tier
A31: Cloud Run | B31: 9B46-8DDB-2AC8 | C31: Cloud Run Network Inter Region Data Transfer Out Intercontinental (Excl Oceania) | D31: Network / egress | E31: gibibyte | F31: 1 | G31: 1 | I31: 7.564 | J31: =IFERROR(INDEX('Usage Inputs'!$G:$G,MATCH(B31,'Usage Inputs'!$B:$B,0)),0) | K31: =MAX(0,(IF(H31="",J31,MIN(J31,H31))-G31)) | L31: =K31/F31*I31 | M31: Final tier
A32: Cloud Run | B32: E262-332F-1474 | C32: Cloud Run Network Inter Region Data Transfer Out North America to North America | D32: Network / egress | E32: gibibyte | F32: 1 | G32: 0 | H32: 1 | I32: 0 | J32: =IFERROR(INDEX('Usage Inputs'!$G:$G,MATCH(B32,'Usage Inputs'!$B:$B,0)),0) | K32: =MAX(0,(IF(H32="",J32,MIN(J32,H32))-G32)) | L32: =K32/F32*I32 | M32: Bounded tier
A33: Cloud Run | B33: E262-332F-1474 | C33: Cloud Run Network Inter Region Data Transfer Out North America to North America | D33: Network / egress | E33: gibibyte | F33: 1 | G33: 1 | I33: 0.9455 | J33: =IFERROR(INDEX('Usage Inputs'!$G:$G,MATCH(B33,'Usage Inputs'!$B:$B,0)),0) | K33: =MAX(0,(IF(H33="",J33,MIN(J33,H33))-G33)) | L33: =K33/F33*I33 | M33: Final tier
A34: Cloud Run | B34: DBAA-7594-B9FA | C34: Cloud Run Network Internet Data Transfer Out Intercontinental (Excl Oceania, Africa and China) | D34: Network / egress | E34: gibibyte | F34: 1 | G34: 0 | H34: 10240 | I34: 11.346 | J34: =IFERROR(INDEX('Usage Inputs'!$G:$G,MATCH(B34,'Usage Inputs'!$B:$B,0)),0) | K34: =MAX(0,(IF(H34="",J34,MIN(J34,H34))-G34)) | L34: =K34/F34*I34 | M34: Bounded tier
A35: Cloud Run | B35: DBAA-7594-B9FA | C35: Cloud Run Network Internet Data Transfer Out Intercontinental (Excl Oceania, Africa and China) | D35: Network / egress | E35: gibibyte | F35: 1 | G35: 10240 | H35: 153600 | I35: 8.03675 | J35: =IFERROR(INDEX('Usage Inputs'!$G:$G,MATCH(B35,'Usage Inputs'!$B:$B,0)),0) | K35: =MAX(0,(IF(H35="",J35,MIN(J35,H35))-G35)) | L35: =K35/F35*I35 | M35: Bounded tier
A36: Cloud Run | B36: DBAA-7594-B9FA | C36: Cloud Run Network Internet Data Transfer Out Intercontinental (Excl Oceania, Africa and China) | D36: Network / egress | E36: gibibyte | F36: 1 | G36: 153600 | I36: 7.564 | J36: =IFERROR(INDEX('Usage Inputs'!$G:$G,MATCH(B36,'Usage Inputs'!$B:$B,0)),0) | K36: =MAX(0,(IF(H36="",J36,MIN(J36,H36))-G36)) | L36: =K36/F36*I36 | M36: Final tier
A37: Cloud Run | B37: DF75-E5D2-F9DB | C37: Cloud Run Network Internet Data Transfer Out Intercontinental from/to Oceania | D37: Network / egress | E37: gibibyte | F37: 1 | G37: 0 | H37: 10240 | I37: 17.9645 | J37: =IFERROR(INDEX('Usage Inputs'!$G:$G,MATCH(B37,'Usage Inputs'!$B:$B,0)),0) | K37: =MAX(0,(IF(H37="",J37,MIN(J37,H37))-G37)) | L37: =K37/F37*I37 | M37: Bounded tier
A38: Cloud Run | B38: DF75-E5D2-F9DB | C38: Cloud Run Network Internet Data Transfer Out Intercontinental from/to Oceania | D38: Network / egress | E38: gibibyte | F38: 1 | G38: 10240 | H38: 153600 | I38: 15.128 | J38: =IFERROR(INDEX('Usage Inputs'!$G:$G,MATCH(B38,'Usage Inputs'!$B:$B,0)),0) | K38: =MAX(0,(IF(H38="",J38,MIN(J38,H38))-G38)) | L38: =K38/F38*I38 | M38: Bounded tier
A39: Cloud Run | B39: DF75-E5D2-F9DB | C39: Cloud Run Network Internet Data Transfer Out Intercontinental from/to Oceania | D39: Network / egress | E39: gibibyte | F39: 1 | G39: 153600 | I39: 14.1825 | J39: =IFERROR(INDEX('Usage Inputs'!$G:$G,MATCH(B39,'Usage Inputs'!$B:$B,0)),0) | K39: =MAX(0,(IF(H39="",J39,MIN(J39,H39))-G39)) | L39: =K39/F39*I39 | M39: Final tier
A40: Cloud Run | B40: DDFD-AE42-E219 | C40: Cloud Run Network Internet Data Transfer Out North America to North America | D40: Network / egress | E40: gibibyte | F40: 1 | G40: 0 | H40: 1 | I40: 0 | J40: =IFERROR(INDEX('Usage Inputs'!$G:$G,MATCH(B40,'Usage Inputs'!$B:$B,0)),0) | K40: =MAX(0,(IF(H40="",J40,MIN(J40,H40))-G40)) | L40: =K40/F40*I40 | M40: Bounded tier
A41: Cloud Run | B41: DDFD-AE42-E219 | C41: Cloud Run Network Internet Data Transfer Out North America to North America | D41: Network / egress | E41: gibibyte | F41: 1 | G41: 1 | H41: 10240 | I41: 9.92775 | J41: =IFERROR(INDEX('Usage Inputs'!$G:$G,MATCH(B41,'Usage Inputs'!$B:$B,0)),0) | K41: =MAX(0,(IF(H41="",J41,MIN(J41,H41))-G41)) | L41: =K41/F41*I41 | M41: Bounded tier
A42: Cloud Run | B42: DDFD-AE42-E219 | C42: Cloud Run Network Internet Data Transfer Out North America to North America | D42: Network / egress | E42: gibibyte | F42: 1 | G42: 10240 | H42: 153600 | I42: 7.564 | J42: =IFERROR(INDEX('Usage Inputs'!$G:$G,MATCH(B42,'Usage Inputs'!$B:$B,0)),0) | K42: =MAX(0,(IF(H42="",J42,MIN(J42,H42))-G42)) | L42: =K42/F42*I42 | M42: Bounded tier
A43: Cloud Run | B43: DDFD-AE42-E219 | C43: Cloud Run Network Internet Data Transfer Out North America to North America | D43: Network / egress | E43: gibibyte | F43: 1 | G43: 153600 | I43: 5.673 | J43: =IFERROR(INDEX('Usage Inputs'!$G:$G,MATCH(B43,'Usage Inputs'!$B:$B,0)),0) | K43: =MAX(0,(IF(H43="",J43,MIN(J43,H43))-G43)) | L43: =K43/F43*I43 | M43: Final tier
A44: Cloud Run | B44: EF10-B23A-2545 | C44: Cloud Run Network Intra Region Data Transfer | D44: Network / egress | E44: gibibyte | F44: 1 | G44: 0 | I44: 0 | J44: =IFERROR(INDEX('Usage Inputs'!$G:$G,MATCH(B44,'Usage Inputs'!$B:$B,0)),0) | K44: =MAX(0,(IF(H44="",J44,MIN(J44,H44))-G44)) | L44: =K44/F44*I44 | M44: Final tier
A45: Cloud Run | B45: 257B-2A84-3396 | C45: Jobs CPU in us-central1 | D45: Compute time | E45: second | F45: 1 | G45: 0 | I45: 0.0017019 | J45: =IFERROR(INDEX('Usage Inputs'!$G:$G,MATCH(B45,'Usage Inputs'!$B:$B,0)),0) | K45: =MAX(0,(IF(H45="",J45,MIN(J45,H45))-G45)) | L45: =K45/F45*I45 | M45: Final tier
A46: Cloud Run | B46: 8A79-9F45-5F32 | C46: Jobs Memory in us-central1 | D46: Compute time | E46: gibibyte second | F46: 1 | G46: 0 | I46: 0.0001891 | J46: =IFERROR(INDEX('Usage Inputs'!$G:$G,MATCH(B46,'Usage Inputs'!$B:$B,0)),0) | K46: =MAX(0,(IF(H46="",J46,MIN(J46,H46))-G46)) | L46: =K46/F46*I46 | M46: Final tier
A47: Cloud Run | B47: 2DA5-55D3-E679 | C47: Requests | D47: Requests / operations | E47: count | F47: 1000000 | G47: 0 | H47: 2000000 | I47: 0 | J47: =IFERROR(INDEX('Usage Inputs'!$G:$G,MATCH(B47,'Usage Inputs'!$B:$B,0)),0) | K47: =MAX(0,(IF(H47="",J47,MIN(J47,H47))-G47)) | L47: =K47/F47*I47 | M47: Bounded tier
A48: Cloud Run | B48: 2DA5-55D3-E679 | C48: Requests | D48: Requests / operations | E48: count | F48: 1000000 | G48: 2000000 | I48: 37.82 | J48: =IFERROR(INDEX('Usage Inputs'!$G:$G,MATCH(B48,'Usage Inputs'!$B:$B,0)),0) | K48: =MAX(0,(IF(H48="",J48,MIN(J48,H48))-G48)) | L48: =K48/F48*I48 | M48: Final tier
A49: Cloud Run | B49: 4856-B847-F1EB | C49: Services CPU (Request-based billing) | D49: Compute time | E49: second | F49: 1 | G49: 0 | I49: 0.0022692 | J49: =IFERROR(INDEX('Usage Inputs'!$G:$G,MATCH(B49,'Usage Inputs'!$B:$B,0)),0) | K49: =MAX(0,(IF(H49="",J49,MIN(J49,H49))-G49)) | L49: =K49/F49*I49 | M49: Final tier
A50: Cloud Run | B50: 02A2-9231-36A6 | C50: Services Memory (Request-based billing) | D50: Compute time | E50: gibibyte second | F50: 1 | G50: 0 | I50: 0.000236375 | J50: =IFERROR(INDEX('Usage Inputs'!$G:$G,MATCH(B50,'Usage Inputs'!$B:$B,0)),0) | K50: =MAX(0,(IF(H50="",J50,MIN(J50,H50))-G50)) | L50: =K50/F50*I50 | M50: Final tier
A51: Cloud Run | B51: 7EBB-8579-2C98 | C51: Services Min Instance CPU (Request-based billing) | D51: Compute time | E51: second | F51: 1 | G51: 0 | I51: 0.000236375 | J51: =IFERROR(INDEX('Usage Inputs'!$G:$G,MATCH(B51,'Usage Inputs'!$B:$B,0)),0) | K51: =MAX(0,(IF(H51="",J51,MIN(J51,H51))-G51)) | L51: =K51/F51*I51 | M51: Final tier
A52: Cloud Run | B52: 740D-08F2-7A11 | C52: Services Min Instance Memory (Request-based billing) | D52: Compute time | E52: gibibyte second | F52: 1 | G52: 0 | I52: 0.000236375 | J52: =IFERROR(INDEX('Usage Inputs'!$G:$G,MATCH(B52,'Usage Inputs'!$B:$B,0)),0) | K52: =MAX(0,(IF(H52="",J52,MIN(J52,H52))-G52)) | L52: =K52/F52*I52 | M52: Final tier
A53: Cloud SQL | B53: 00AF-5292-3D5D | C53: CloudSQL Free Tier Data Cache Storage | D53: Storage / retention | E53: gibibyte month | F53: 1 | G53: 0 | I53: 0 | J53: =IFERROR(INDEX('Usage Inputs'!$G:$G,MATCH(B53,'Usage Inputs'!$B:$B,0)),0) | K53: =MAX(0,(IF(H53="",J53,MIN(J53,H53))-G53)) | L53: =K53/F53*I53 | M53: Final tier
A54: Cloud SQL | B54: 211D-2EB8-B4E3 | C54: CloudSQL Free Tier Instance RAM | D54: Other | E54: gibibyte hour | F54: 1 | G54: 0 | I54: 0 | J54: =IFERROR(INDEX('Usage Inputs'!$G:$G,MATCH(B54,'Usage Inputs'!$B:$B,0)),0) | K54: =MAX(0,(IF(H54="",J54,MIN(J54,H54))-G54)) | L54: =K54/F54*I54 | M54: Final tier
A55: Cloud SQL | B55: A20B-E6B8-A643 | C55: CloudSQL Free Tier Instance vCPU Cores | D55: Compute time | E55: hour | F55: 1 | G55: 0 | I55: 0 | J55: =IFERROR(INDEX('Usage Inputs'!$G:$G,MATCH(B55,'Usage Inputs'!$B:$B,0)),0) | K55: =MAX(0,(IF(H55="",J55,MIN(J55,H55))-G55)) | L55: =K55/F55*I55 | M55: Final tier
A56: Cloud SQL | B56: E577-1705-5479 | C56: CloudSQL Free Tier Standard storage | D56: Storage / retention | E56: gibibyte month | F56: 1 | G56: 0 | I56: 0 | J56: =IFERROR(INDEX('Usage Inputs'!$G:$G,MATCH(B56,'Usage Inputs'!$B:$B,0)),0) | K56: =MAX(0,(IF(H56="",J56,MIN(J56,H56))-G56)) | L56: =K56/F56*I56 | M56: Final tier
A57: Cloud Scheduler | B57: A5D6-43A2-28A7 | C57: Jobs | D57: Other | E57: count | F57: 31 | G57: 0 | H57: 93 | I57: 0 | J57: =IFERROR(INDEX('Usage Inputs'!$G:$G,MATCH(B57,'Usage Inputs'!$B:$B,0)),0) | K57: =MAX(0,(IF(H57="",J57,MIN(J57,H57))-G57)) | L57: =K57/F57*I57 | M57: Bounded tier
A58: Cloud Scheduler | B58: A5D6-43A2-28A7 | C58: Jobs | D58: Other | E58: count | F58: 31 | G58: 93 | I58: 9.455 | J58: =IFERROR(INDEX('Usage Inputs'!$G:$G,MATCH(B58,'Usage Inputs'!$B:$B,0)),0) | K58: =MAX(0,(IF(H58="",J58,MIN(J58,H58))-G58)) | L58: =K58/F58*I58 | M58: Final tier
A59: Cloud Storage | B59: 1F8B-71B0-3D1B | C59: Download APAC | D59: Network / egress | E59: gibibyte | F59: 1 | G59: 0 | H59: 100 | I59: 0 | J59: =IFERROR(INDEX('Usage Inputs'!$G:$G,MATCH(B59,'Usage Inputs'!$B:$B,0)),0) | K59: =MAX(0,(IF(H59="",J59,MIN(J59,H59))-G59)) | L59: =K59/F59*I59 | M59: Bounded tier
A60: Cloud Storage | B60: 1F8B-71B0-3D1B | C60: Download APAC | D60: Network / egress | E60: gibibyte | F60: 1 | G60: 100 | H60: 1024 | I60: 11.346 | J60: =IFERROR(INDEX('Usage Inputs'!$G:$G,MATCH(B60,'Usage Inputs'!$B:$B,0)),0) | K60: =MAX(0,(IF(H60="",J60,MIN(J60,H60))-G60)) | L60: =K60/F60*I60 | M60: Bounded tier
A61: Cloud Storage | B61: 1F8B-71B0-3D1B | C61: Download APAC | D61: Network / egress | E61: gibibyte | F61: 1 | G61: 1024 | H61: 10240 | I61: 10.4005 | J61: =IFERROR(INDEX('Usage Inputs'!$G:$G,MATCH(B61,'Usage Inputs'!$B:$B,0)),0) | K61: =MAX(0,(IF(H61="",J61,MIN(J61,H61))-G61)) | L61: =K61/F61*I61 | M61: Bounded tier
A62: Cloud Storage | B62: 1F8B-71B0-3D1B | C62: Download APAC | D62: Network / egress | E62: gibibyte | F62: 1 | G62: 10240 | I62: 7.564 | J62: =IFERROR(INDEX('Usage Inputs'!$G:$G,MATCH(B62,'Usage Inputs'!$B:$B,0)),0) | K62: =MAX(0,(IF(H62="",J62,MIN(J62,H62))-G62)) | L62: =K62/F62*I62 | M62: Final tier
A63: Cloud Storage | B63: 9ADA-9AED-1B24 | C63: Multi-Region Standard Class A Operations | D63: Storage / retention | E63: count | F63: 1000 | G63: 0 | I63: 0.9455 | J63: =IFERROR(INDEX('Usage Inputs'!$G:$G,MATCH(B63,'Usage Inputs'!$B:$B,0)),0) | K63: =MAX(0,(IF(H63="",J63,MIN(J63,H63))-G63)) | L63: =K63/F63*I63 | M63: Final tier
A64: Cloud Storage | B64: 8AE7-5BBD-8F38 | C64: Multi-Region Standard Class B Operations | D64: Storage / retention | E64: count | F64: 1000 | G64: 0 | I64: 0.03782 | J64: =IFERROR(INDEX('Usage Inputs'!$G:$G,MATCH(B64,'Usage Inputs'!$B:$B,0)),0) | K64: =MAX(0,(IF(H64="",J64,MIN(J64,H64))-G64)) | L64: =K64/F64*I64 | M64: Final tier
A65: Cloud Storage | B65: B1FE-19F7-6D1B | C65: NA-based Storage Data Transfer Out via peered/interconnect network | D65: Network / egress | E65: gibibyte | F65: 1 | G65: 0 | I65: 7.564 | J65: =IFERROR(INDEX('Usage Inputs'!$G:$G,MATCH(B65,'Usage Inputs'!$B:$B,0)),0) | K65: =MAX(0,(IF(H65="",J65,MIN(J65,H65))-G65)) | L65: =K65/F65*I65 | M65: Final tier
A66: Cloud Storage | B66: 3C8A-99C5-F47B | C66: Network Data Transfer GCP Multi-region within Northern America | D66: Network / egress | E66: gibibyte | F66: 1 | G66: 0 | I66: 1.891 | J66: =IFERROR(INDEX('Usage Inputs'!$G:$G,MATCH(B66,'Usage Inputs'!$B:$B,0)),0) | K66: =MAX(0,(IF(H66="",J66,MIN(J66,H66))-G66)) | L66: =K66/F66*I66 | M66: Final tier
A67: Cloud Storage | B67: AED0-3315-7B11 | C67: Network Data Transfer GCP Replication within Northern America | D67: Network / egress | E67: gibibyte | F67: 1 | G67: 0 | I67: 1.891 | J67: =IFERROR(INDEX('Usage Inputs'!$G:$G,MATCH(B67,'Usage Inputs'!$B:$B,0)),0) | K67: =MAX(0,(IF(H67="",J67,MIN(J67,H67))-G67)) | L67: =K67/F67*I67 | M67: Final tier
A68: Cloud Storage | B68: 4DBF-185F-A415 | C68: Regional Standard Class A Operations | D68: Storage / retention | E68: count | F68: 1000 | G68: 0 | H68: 5000 | I68: 0 | J68: =IFERROR(INDEX('Usage Inputs'!$G:$G,MATCH(B68,'Usage Inputs'!$B:$B,0)),0) | K68: =MAX(0,(IF(H68="",J68,MIN(J68,H68))-G68)) | L68: =K68/F68*I68 | M68: Bounded tier
A69: Cloud Storage | B69: 4DBF-185F-A415 | C69: Regional Standard Class A Operations | D69: Storage / retention | E69: count | F69: 1000 | G69: 5000 | I69: 0.47275 | J69: =IFERROR(INDEX('Usage Inputs'!$G:$G,MATCH(B69,'Usage Inputs'!$B:$B,0)),0) | K69: =MAX(0,(IF(H69="",J69,MIN(J69,H69))-G69)) | L69: =K69/F69*I69 | M69: Final tier
A70: Cloud Storage | B70: 7870-010B-2763 | C70: Regional Standard Class B Operations | D70: Storage / retention | E70: count | F70: 1000 | G70: 0 | H70: 50000 | I70: 0 | J70: =IFERROR(INDEX('Usage Inputs'!$G:$G,MATCH(B70,'Usage Inputs'!$B:$B,0)),0) | K70: =MAX(0,(IF(H70="",J70,MIN(J70,H70))-G70)) | L70: =K70/F70*I70 | M70: Bounded tier
A71: Cloud Storage | B71: 7870-010B-2763 | C71: Regional Standard Class B Operations | D71: Storage / retention | E71: count | F71: 1000 | G71: 50000 | I71: 0.03782 | J71: =IFERROR(INDEX('Usage Inputs'!$G:$G,MATCH(B71,'Usage Inputs'!$B:$B,0)),0) | K71: =MAX(0,(IF(H71="",J71,MIN(J71,H71))-G71)) | L71: =K71/F71*I71 | M71: Final tier
A72: Cloud Storage | B72: 0D5D-6E23-4250 | C72: Standard Storage US Multi-region | D72: Storage / retention | E72: gibibyte month | F72: 1 | G72: 0 | I72: 2.4583 | J72: =IFERROR(INDEX('Usage Inputs'!$G:$G,MATCH(B72,'Usage Inputs'!$B:$B,0)),0) | K72: =MAX(0,(IF(H72="",J72,MIN(J72,H72))-G72)) | L72: =K72/F72*I72 | M72: Final tier
A73: Cloud Storage | B73: E5F0-6A5D-7BAD | C73: Standard Storage US Regional | D73: Storage / retention | E73: gibibyte month | F73: 1 | G73: 0 | H73: 5 | I73: 0 | J73: =IFERROR(INDEX('Usage Inputs'!$G:$G,MATCH(B73,'Usage Inputs'!$B:$B,0)),0) | K73: =MAX(0,(IF(H73="",J73,MIN(J73,H73))-G73)) | L73: =K73/F73*I73 | M73: Bounded tier
A74: Cloud Storage | B74: E5F0-6A5D-7BAD | C74: Standard Storage US Regional | D74: Storage / retention | E74: gibibyte month | F74: 1 | G74: 5 | I74: 1.891 | J74: =IFERROR(INDEX('Usage Inputs'!$G:$G,MATCH(B74,'Usage Inputs'!$B:$B,0)),0) | K74: =MAX(0,(IF(H74="",J74,MIN(J74,H74))-G74)) | L74: =K74/F74*I74 | M74: Final tier
A75: Cloud Tasks | B75: FE08-0A74-7AFD | C75: Cloud Tasks GOOGLE-API Data Transfer Out | D75: Network / egress | E75: gibibyte | F75: 1 | G75: 0 | I75: 0 | J75: =IFERROR(INDEX('Usage Inputs'!$G:$G,MATCH(B75,'Usage Inputs'!$B:$B,0)),0) | K75: =MAX(0,(IF(H75="",J75,MIN(J75,H75))-G75)) | L75: =K75/F75*I75 | M75: Final tier
A76: Cloud Tasks | B76: 378A-D762-1F74 | C76: Operations | D76: Requests / operations | E76: count | F76: 1000000 | G76: 0 | H76: 1000000 | I76: 0 | J76: =IFERROR(INDEX('Usage Inputs'!$G:$G,MATCH(B76,'Usage Inputs'!$B:$B,0)),0) | K76: =MAX(0,(IF(H76="",J76,MIN(J76,H76))-G76)) | L76: =K76/F76*I76 | M76: Bounded tier
A77: Cloud Tasks | B77: 378A-D762-1F74 | C77: Operations | D77: Requests / operations | E77: count | F77: 1000000 | G77: 1000000 | I77: 37.82 | J77: =IFERROR(INDEX('Usage Inputs'!$G:$G,MATCH(B77,'Usage Inputs'!$B:$B,0)),0) | K77: =MAX(0,(IF(H77="",J77,MIN(J77,H77))-G77)) | L77: =K77/F77*I77 | M77: Final tier
A78: Secret Manager | B78: EBA7-264F-2D2C | C78: Secret access operations | D78: Requests / operations | E78: count | F78: 10000 | G78: 0 | H78: 10000 | I78: 0 | J78: =IFERROR(INDEX('Usage Inputs'!$G:$G,MATCH(B78,'Usage Inputs'!$B:$B,0)),0) | K78: =MAX(0,(IF(H78="",J78,MIN(J78,H78))-G78)) | L78: =K78/F78*I78 | M78: Bounded tier
A79: Secret Manager | B79: EBA7-264F-2D2C | C79: Secret access operations | D79: Requests / operations | E79: count | F79: 10000 | G79: 10000 | I79: 2.8365 | J79: =IFERROR(INDEX('Usage Inputs'!$G:$G,MATCH(B79,'Usage Inputs'!$B:$B,0)),0) | K79: =MAX(0,(IF(H79="",J79,MIN(J79,H79))-G79)) | L79: =K79/F79*I79 | M79: Final tier
A80: Secret Manager | B80: 7756-ADEF-84F4 | C80: Secret version replica storage | D80: Storage / retention | E80: month | F80: 1 | G80: 0 | H80: 6 | I80: 0 | J80: =IFERROR(INDEX('Usage Inputs'!$G:$G,MATCH(B80,'Usage Inputs'!$B:$B,0)),0) | K80: =MAX(0,(IF(H80="",J80,MIN(J80,H80))-G80)) | L80: =K80/F80*I80 | M80: Bounded tier
A81: Secret Manager | B81: 7756-ADEF-84F4 | C81: Secret version replica storage | D81: Storage / retention | E81: month | F81: 1 | G81: 6 | I81: 5.673 | J81: =IFERROR(INDEX('Usage Inputs'!$G:$G,MATCH(B81,'Usage Inputs'!$B:$B,0)),0) | K81: =MAX(0,(IF(H81="",J81,MIN(J81,H81))-G81)) | L81: =K81/F81*I81 | M81: Final tier

Sheet Source Pricing
A1: Source Pricing
A2: Converted from the provided Numbers workbook; category and normalized-rate columns added for analysis.
A4: Google service | B4: Service description | C4: Service ID | D4: SKU ID | E4: SKU description | F4: Consumption model description | G4: Product taxonomy | H4: Unit description | I4: Per unit quantity | J4: Tiered usage start | K4: List price (INR) | L4: Category | M4: Normalized rate | N4: Normalized unit
A5: GCP | B5: Cloud DNS | C5: FA26-5236-B8B5 | D5: 6DFF-5025-A128 | E5: DNS Query (port 53) | F5: Default | G5: GCP > Network > Cloud DNS > Other | H5: count | I5: 1000000 | J5: 0 | K5: 37.82 | L5: Requests / operations | M5: 37.82 | N5: per 1,000,000 count
A6: GCP | B6: Cloud DNS | C6: FA26-5236-B8B5 | D6: 6DFF-5025-A128 | E6: DNS Query (port 53) | F6: Default | G6: GCP > Network > Cloud DNS > Other | H6: count | I6: 1000000 | J6: 1000000000 | K6: 18.91 | L6: Requests / operations | M6: 18.91 | N6: per 1,000,000 count
A7: GCP | B7: Cloud DNS | C7: FA26-5236-B8B5 | D7: 8C22-6FC3-D478 | E7: ManagedZone | F7: Default | G7: GCP > Network > Cloud DNS > Other | H7: month | I7: 1 | J7: 0 | K7: 18.91 | L7: Other | M7: 18.91 | N7: per month
A8: GCP | B8: Cloud DNS | C8: FA26-5236-B8B5 | D8: 8C22-6FC3-D478 | E8: ManagedZone | F8: Default | G8: GCP > Network > Cloud DNS > Other | H8: month | I8: 1 | J8: 25 | K8: 9.455 | L8: Other | M8: 9.455 | N8: per month
A9: GCP | B9: Cloud DNS | C9: FA26-5236-B8B5 | D9: 8C22-6FC3-D478 | E9: ManagedZone | F9: Default | G9: GCP > Network > Cloud DNS > Other | H9: month | I9: 1 | J9: 10000 | K9: 2.8365 | L9: Other | M9: 2.8365 | N9: per month
A10: GCP | B10: Cloud SQL | C10: 9662-B51E-5089 | D10: 00AF-5292-3D5D | E10: CloudSQL Free Tier Data Cache Storage | F10: Default | G10: GCP > Databases > Cloud SQL > Free Instance | H10: gibibyte month | I10: 1 | J10: 0 | K10: 0 | L10: Storage / retention | M10: 0 | N10: per gibibyte month
A11: GCP | B11: Cloud SQL | C11: 9662-B51E-5089 | D11: A20B-E6B8-A643 | E11: CloudSQL Free Tier Instance vCPU Cores | F11: Default | G11: GCP > Databases > Cloud SQL > Free Instance | H11: hour | I11: 1 | J11: 0 | K11: 0 | L11: Compute time | M11: 0 | N11: per hour
A12: GCP | B12: Cloud SQL | C12: 9662-B51E-5089 | D12: 211D-2EB8-B4E3 | E12: CloudSQL Free Tier Instance RAM | F12: Default | G12: GCP > Databases > Cloud SQL > Free Instance | H12: gibibyte hour | I12: 1 | J12: 0 | K12: 0 | L12: Other | M12: 0 | N12: per gibibyte hour
A13: GCP | B13: Cloud SQL | C13: 9662-B51E-5089 | D13: E577-1705-5479 | E13: CloudSQL Free Tier Standard storage | F13: Default | G13: GCP > Databases > Cloud SQL > Free Instance | H13: gibibyte month | I13: 1 | J13: 0 | K13: 0 | L13: Storage / retention | M13: 0 | N13: per gibibyte month
A14: GCP | B14: Cloud Storage | C14: 95FF-2EF5-5EA1 | D14: 1F8B-71B0-3D1B | E14: Download APAC | F14: Default | G14: GCP > Network > Egress > GCS > Premium | H14: gibibyte | I14: 1 | J14: 0 | K14: 0 | L14: Network / egress | M14: 0 | N14: per gibibyte
A15: GCP | B15: Cloud Storage | C15: 95FF-2EF5-5EA1 | D15: 1F8B-71B0-3D1B | E15: Download APAC | F15: Default | G15: GCP > Network > Egress > GCS > Premium | H15: gibibyte | I15: 1 | J15: 100 | K15: 11.346 | L15: Network / egress | M15: 11.346 | N15: per gibibyte
A16: GCP | B16: Cloud Storage | C16: 95FF-2EF5-5EA1 | D16: 1F8B-71B0-3D1B | E16: Download APAC | F16: Default | G16: GCP > Network > Egress > GCS > Premium | H16: gibibyte | I16: 1 | J16: 1024 | K16: 10.4005 | L16: Network / egress | M16: 10.4005 | N16: per gibibyte
... A113: GCP | B113: Secret Manager | C113: EE82-7A5E-871C | D113: 7756-ADEF-84F4 | E113: Secret version replica storage | F113: Default | G113: GCP > Cloud Security > Cloud Security - Other > Other Security Platform > Other Platform > Secret Manager > Other | H113: month | I113: 1 | J113: 6 | K113: 5.673 | L113: Storage / retention | M113: 5.673 | N113: per month

Sheet Checks
A1: Checks
A2: Basic workbook integrity checks.
A3: Check | B3: Actual | C3: Expected | D3: OK? | E3: Notes
A4: Source rows loaded | B4: 109 | C4: 109 | D4: =B4=C4 | E4: Rows should match the converted source table.
A5: Unique SKUs present | B5: 46 | C5: 46 | D5: =B5=C5 | E5: Guard against empty SKU extraction.
A6: Estimator rows | B6: 77 | C6: 77 | D6: =B6=C6 | E6: Estimator uses Default model rows only.
A7: Usage input rows | B7: 46 | C7: 46 | D7: =B7=C7 | E7: One usage input per Default SKU.
